metrofsm.v
module metrofsm(
    input clk,rst,
    input [3:0] access_code ,
    input validate_code,
    output reg open_access_door ,
    output [1:0] state_out
  );

  parameter IDLE = 2'b00 ;
  parameter CHECK_CODE = 2'b01 ;
  parameter ACCESS_GRANTED = 2'b10 ;

  reg [3:0] counter ;
  reg [1:0] ps,ns ;


  always@(posedge clk or negedge rst)
  begin
    if(!rst)
    begin
      ps <= IDLE ;
    end
    else
      ps <= ns ;

   case(ps)
      IDLE :
      begin
        open_access_door <= 1'b0 ;
      end
      CHECK_CODE :
      begin
        open_access_door <= 1'b0 ;
      end

      ACCESS_GRANTED :
      begin
        if(counter != 4'hF)
          open_access_door <= 1'b1 ;
        else
          open_access_door <= 1'b0 ;
      end
    endcase
end
  
assign state_out = ps ;

  always @(posedge clk or negedge rst)
  begin
    if(!rst)
    counter <= 4'h0 ;
    else if(ps == ACCESS_GRANTED)
      counter <= counter + 4'h1;
    else
      counter <= 4'd0;
  end

  always@(*)
  begin
    ns = IDLE ;

    case(ps)

      IDLE :
      begin 
        if(validate_code)
          ns = CHECK_CODE ;
        else
          ns = IDLE ;
      end

      CHECK_CODE:
      begin
        if((access_code >= 4'd4) && (access_code <= 4'd11))
          ns = ACCESS_GRANTED ;
        else
          ns = IDLE ;

      end

      ACCESS_GRANTED:
      begin 
       
        if(counter == 4'hF)
          ns = IDLE ;
        else
          ns = ACCESS_GRANTED ;
      end

      default :
        ns = IDLE ;

    endcase
  end


endmodule

metrofsm_tb.v
`timescale 1ns/1ps
`include "metrofsm.v"

module metrofsm_tb;

  reg clk;
  reg rst;
  reg [3:0] access_code;
  reg validate_code;

  wire open_access_door;
  wire [1:0] state_out;

  // DUT
  metrofsm dut (
    .clk(clk),
    .rst(rst),
    .access_code(access_code),
    .validate_code(validate_code),
    .open_access_door(open_access_door),
    .state_out(state_out)
  );

  // -------------------------
  // Clock: 10 ns period
  // -------------------------
  always #5 clk = ~clk;

  // -------------------------
  // Initial values
  // -------------------------
  initial begin
    clk = 0;
    rst = 0;
    access_code = 4'd0;
    validate_code = 1'b0;
  end

  // -------------------------
  // Reset
  // -------------------------
  initial begin
    #12;
    rst = 1'b1;
  end

  // -------------------------
  // Stimulus
  // -------------------------
  initial begin
    // Wait for reset release
    @(posedge rst);

    // ---------- VALID ACCESS ----------
    @(negedge clk);
    access_code   = 4'd9;   // valid code (4–11)
    validate_code = 1'b1;

    @(negedge clk);
    validate_code = 1'b0;   // IMPORTANT: pulse ends

    // Wait while ACCESS_GRANTED runs
    repeat (20) @(posedge clk);

    // ---------- INVALID ACCESS ----------
    @(negedge clk);
    access_code   = 4'd2;   // invalid code
    validate_code = 1'b1;

    @(negedge clk);
    validate_code = 1'b0;

    repeat (10) @(posedge clk);

    $finish;
  end

  // -------------------------
  // Dump
  // -------------------------
  initial begin
    $dumpfile("metrofsm.vcd");
    $dumpvars(0, metrofsm_tb);
  end

endmodule

metrofsm.vcd
$date
	Thu Jan 08 15:19:19 2026
$end
$version
	Icarus Verilog
$end
$timescale
	1ps
$end
$scope module metrofsm_tb $end
$var wire 2 ! state_out [1:0] $end
$var wire 1 " open_access_door $end
$var reg 4 # access_code [3:0] $end
$var reg 1 $ clk $end
$var reg 1 % rst $end
$var reg 1 & validate_code $end
$scope module dut $end
$var wire 4 ' access_code [3:0] $end
$var wire 1 $ clk $end
$var wire 1 % rst $end
$var wire 2 ( state_out [1:0] $end
$var wire 1 & validate_code $end
$var reg 4 ) counter [3:0] $end
$var reg 2 * ns [1:0] $end
$var reg 1 " open_access_door $end
$var reg 2 + ps [1:0] $end
$upscope $end
$upscope $end
$enddefinitions $end
#0
$dumpvars
b0 +
b0 *
b0 )
b0 (
b0 '
0&
0%
0$
b0 #
x"
b0 !
$end
#5000
0"
1$
#10000
0$
#12000
1%
#15000
1$
#20000
b1 *
1&
b1001 #
b1001 '
0$
#25000
b10 *
b1 !
b1 (
b1 +
1$
#30000
b10 *
0&
0$
#35000
b10 *
b10 !
b10 (
b10 +
1$
#40000
0$
#45000
b10 *
b1 )
1"
1$
#50000
0$
#55000
b10 *
b10 )
1$
#60000
0$
#65000
b10 *
b11 )
1$
#70000
0$
#75000
b10 *
b100 )
1$
#80000
0$
#85000
b10 *
b101 )
1$
#90000
0$
#95000
b10 *
b110 )
1$
#100000
0$
#105000
b10 *
b111 )
1$
#110000
0$
#115000
b10 *
b1000 )
1$
#120000
0$
#125000
b10 *
b1001 )
1$
#130000
0$
#135000
b10 *
b1010 )
1$
#140000
0$
#145000
b10 *
b1011 )
1$
#150000
0$
#155000
b10 *
b1100 )
1$
#160000
0$
#165000
b10 *
b1101 )
1$
#170000
0$
#175000
b10 *
b1110 )
1$
#180000
0$
#185000
b0 *
b1111 )
1$
#190000
0$
#195000
0"
b0 !
b0 (
b0 +
b0 )
1$
#200000
0$
#205000
1$
#210000
0$
#215000
1$
#220000
0$
#225000
1$
#230000
b1 *
1&
b10 #
b10 '
0$
#235000
b0 *
b1 !
b1 (
b1 +
1$
#240000
0&
0$
#245000
b0 !
b0 (
b0 +
1$
